{
  "VehicleTags": {
    "items": [
      "mr-resize-1.5",
      "unit_vehicle",
      "omni_tank",
      "unit_assault",
      "unit_tracks",
      "unit_release",
      "unit_lance_assassin",
      "unit_lance_vanguard",
      "unit_advanced",
      "unit_bracket_high",
      "republic",
      "comstar",
      "steiner",
      "davion"
    ],
    "tagSetSourceFile": ""
  },
  "ChassisID": "vehiclechassisdef_AJAX_A",
  "Description": {
    "Cost": 20348715,
    "Rarity": 0,
    "Purchasable": false,
    "UIName": "Ajax A",
    "Id": "vehicledef_AJAX_A",
    "Name": "Ajax A",
    "Details": "The Ajax Assault Tank is an Omni-capable combat vehicle that is the follow-up to GM's Challenger X MBT. The Ajax follows on the heels of the successful Manteuffel OmniVehicle. The Ajax is slow, only capable of attaining speeds up to 54 km/h. Since speed is not its defense, the designers gave the Ajax nineteen tons of armor. The room for all of this armor comes from the XL Engine the Ajax uses for power. \n\n<b><color=#ffcc00>Fusion: Expensive engine that works in a Vacuum.</color></b>\n\n<b><color=#ffcc00>Movement: 3/5 Hex: 90/150 Meters.</color></b>\n\n<color=#ffcc00><b>Armor:</b> Armor\n<b>Structure:</b> Structure\n<b>Values       A        S  </b>\n<b>Front</b>       365     45\n<b>Left</b>         300     45\n<b>Right</b>       300     45\n<b>Rear</b>        220     45\n<b>Turret</b>      350     45\n\n<b>Total</b>      1535    225</color>\n\n<color=#ff0000>Quirk: Improved Communications</color>\n\n<color=#ffcc00> Omni Vehicle</color>",
    "Icon": "Ajax"
  },
  "Locations": [
    {
      "Location": "Front",
      "CurrentArmor": 365,
      "CurrentInternalStructure": 45,
      "AssignedArmor": 365,
      "DamageLevel": "Functional"
    },
    {
      "Location": "Left",
      "CurrentArmor": 300,
      "CurrentInternalStructure": 45,
      "AssignedArmor": 300,
      "DamageLevel": "Functional"
    },
    {
      "Location": "Right",
      "CurrentArmor": 300,
      "CurrentInternalStructure": 45,
      "AssignedArmor": 300,
      "DamageLevel": "Functional"
    },
    {
      "Location": "Rear",
      "CurrentArmor": 220,
      "CurrentInternalStructure": 45,
      "AssignedArmor": 220,
      "DamageLevel": "Functional"
    },
    {
      "Location": "Turret",
      "CurrentArmor": 350,
      "CurrentInternalStructure": 45,
      "AssignedArmor": 350,
      "DamageLevel": "Functional"
    }
  ],
  "inventory": [
    {
      "MountedLocation": "Turret",
      "ComponentDefID": "Weapon_Autocannon_RAC_5",
      "ComponentDefType": "Weapon",
      "HardpointSlot": 0,
      "DamageLevel": "Functional"
    },
    {
      "MountedLocation": "Turret",
      "ComponentDefID": "Weapon_Autocannon_RAC_5",
      "ComponentDefType": "Weapon",
      "HardpointSlot": 0,
      "DamageLevel": "Functional"
    },
    {
      "MountedLocation": "Turret",
      "ComponentDefID": "Weapon_Autocannon_RAC_5",
      "ComponentDefType": "Weapon",
      "HardpointSlot": 0,
      "DamageLevel": "Functional"
    },
    {
      "MountedLocation": "Turret",
      "ComponentDefID": "Weapon_Laser_ER_Small",
      "ComponentDefType": "Weapon",
      "HardpointSlot": 0,
      "DamageLevel": "Functional"
    },
    {
      "MountedLocation": "Turret",
      "ComponentDefID": "Weapon_Laser_ER_Small",
      "ComponentDefType": "Weapon",
      "HardpointSlot": 0,
      "DamageLevel": "Functional"
    },
    {
      "MountedLocation": "Rear",
      "ComponentDefID": "Ammo_AmmunitionBox_RAC_5",
      "ComponentDefType": "AmmunitionBox",
      "HardpointSlot": -1,
      "DamageLevel": "Functional"
    },
    {
      "MountedLocation": "Rear",
      "ComponentDefID": "Ammo_AmmunitionBox_RAC_5_Double",
      "ComponentDefType": "AmmunitionBox",
      "HardpointSlot": -1,
      "DamageLevel": "Functional"
    },
    {
      "MountedLocation": "Rear",
      "ComponentDefID": "Ammo_AmmunitionBox_RAC_5_Double",
      "ComponentDefType": "AmmunitionBox",
      "HardpointSlot": -1,
      "DamageLevel": "Functional"
    },
    {
      "MountedLocation": "Rear",
      "ComponentDefID": "Ammo_AmmunitionBox_RAC_5_Flak",
      "ComponentDefType": "AmmunitionBox",
      "HardpointSlot": -1,
      "DamageLevel": "Functional"
    },
    {
      "MountedLocation": "Rear",
      "ComponentDefID": "Ammo_AmmunitionBox_RAC_5_Precision",
      "ComponentDefType": "AmmunitionBox",
      "HardpointSlot": -1,
      "DamageLevel": "Functional"
    },
    {
      "MountedLocation": "Rear",
      "ComponentDefID": "Ammo_AmmunitionBox_RAC_5_Precision",
      "ComponentDefType": "AmmunitionBox",
      "HardpointSlot": -1,
      "DamageLevel": "Functional"
    },
    {
      "MountedLocation": "Rear",
      "ComponentDefID": "Ammo_AmmunitionBox_RAC_5_Precision",
      "ComponentDefType": "AmmunitionBox",
      "HardpointSlot": -1,
      "DamageLevel": "Functional"
    },
    {
      "MountedLocation": "Front",
      "ComponentDefID": "Default_Vehicle_Crew_Compartment",
      "ComponentDefType": "Upgrade",
      "HardpointSlot": -1,
      "DamageLevel": "Functional"
    },
    {
      "MountedLocation": "Front",
      "ComponentDefID": "Gear_FCS_Improved",
      "ComponentDefType": "Upgrade",
      "HardpointSlot": -1,
      "DamageLevel": "Functional"
    },
    {
      "MountedLocation": "Front",
      "ComponentDefID": "Gear_Sensors_Improved",
      "ComponentDefType": "Upgrade",
      "HardpointSlot": -1,
      "DamageLevel": "Functional"
    },
    {
      "MountedLocation": "Left",
      "ComponentDefID": "Default_Vehicle_Motive_Tracked_Left",
      "ComponentDefType": "Upgrade",
      "HardpointSlot": -1,
      "DamageLevel": "Functional"
    },
    {
      "MountedLocation": "Right",
      "ComponentDefID": "Default_Vehicle_Motive_Tracked_Right",
      "ComponentDefType": "Upgrade",
      "HardpointSlot": -1,
      "DamageLevel": "Functional"
    },
    {
      "MountedLocation": "Rear",
      "ComponentDefID": "Default_Armor_Standard",
      "ComponentDefType": "Upgrade",
      "HardpointSlot": -1,
      "DamageLevel": "Functional"
    },
    {
      "MountedLocation": "Rear",
      "ComponentDefID": "Default_Structure_Standard",
      "ComponentDefType": "Upgrade",
      "HardpointSlot": -1,
      "DamageLevel": "Functional"
    },
    {
      "MountedLocation": "Rear",
      "ComponentDefID": "Default_Vehicle_Motive_Tracked_Defaultbox",
      "ComponentDefType": "Upgrade",
      "HardpointSlot": -1,
      "DamageLevel": "Functional"
    },
    {
      "MountedLocation": "Rear",
      "ComponentDefID": "Gear_C3_Slave",
      "ComponentDefType": "Upgrade",
      "HardpointSlot": -1,
      "DamageLevel": "Functional"
    },
    {
      "MountedLocation": "Rear",
      "ComponentDefID": "Gear_ECM_Guardian",
      "ComponentDefType": "Upgrade",
      "HardpointSlot": -1,
      "DamageLevel": "Functional"
    },
    {
      "MountedLocation": "Rear",
      "ComponentDefID": "Gear_Vehicle_CASE",
      "ComponentDefType": "Upgrade",
      "HardpointSlot": -1,
      "DamageLevel": "Functional"
    },
    {
      "MountedLocation": "Rear",
      "ComponentDefID": "Quirk_Vehicle_ImprovedComms",
      "ComponentDefType": "Upgrade",
      "HardpointSlot": -1,
      "DamageLevel": "Functional"
    },
    {
      "MountedLocation": "Rear",
      "ComponentDefID": "VehicleTrait_Omni",
      "ComponentDefType": "Upgrade",
      "HardpointSlot": -1,
      "DamageLevel": "Functional"
    },
    {
      "MountedLocation": "Turret",
      "ComponentDefID": "Default_Vehicle_Turret",
      "ComponentDefType": "Upgrade",
      "HardpointSlot": -1,
      "DamageLevel": "Functional"
    },
    {
      "MountedLocation": "Left",
      "ComponentDefID": "Linked_Engine_Size_3",
      "ComponentDefType": "HeatSink",
      "HardpointSlot": -1,
      "DamageLevel": "Functional"
    },
    {
      "MountedLocation": "Right",
      "ComponentDefID": "Linked_Engine_Size_3",
      "ComponentDefType": "HeatSink",
      "HardpointSlot": -1,
      "DamageLevel": "Functional"
    },
    {
      "MountedLocation": "Rear",
      "ComponentDefID": "Gear_EngineCore_270",
      "ComponentDefType": "HeatSink",
      "HardpointSlot": -1,
      "DamageLevel": "Functional"
    },
    {
      "MountedLocation": "Rear",
      "ComponentDefID": "Gear_Engine_XL",
      "ComponentDefType": "HeatSink",
      "HardpointSlot": -1,
      "DamageLevel": "Functional"
    },
    {
      "MountedLocation": "Rear",
      "ComponentDefID": "Gear_Vehicle_EngineCooling_CoolantSystem",
      "ComponentDefType": "HeatSink",
      "HardpointSlot": -1,
      "DamageLevel": "Functional"
    }
  ]
}
