{
  "id": "pilotQuirkDef_pilot_salvageSeeker",
  "tag": "pilot_salvageSeeker",
  "quirkName": "Salvage Seeker",
  "description": "+2 Random Salvage when deployed to the battlefield, +450,000 C-Bill Pilot Upkeep",
  "effectData": [],
  "quirkEffects": [
    {
      "type": "AdditionalSalvage",
      "modifier": 2,
      "secondaryModifier": 0,
      "affectedIds": []
    },
    {
      "type": "PilotCostFactor",
      "modifier": 0.0,
      "secondaryModifier": 450000,
      "affectedIds": []
    }
  ]
}
