{
  "Description": {
    "Id": "TraitDefGuts1",
    "Name": "",
    "Details": "",
    "Icon": ""
  },
  "Type": "GutsEffects",
  "ShortDesc": "+0 Ini Injury & Melee Resist, +5% Resolve Gen",
  "DisplayParams": "ShowInPilotToolTip",
  "ActivationTime": "Passive",
  "EffectData": [
    {
      "durationData": {
        "duration": -1,
        "stackLimit": -1
      },
      "targetingData": {
        "effectTriggerType": "Passive",
        "effectTargetType": "SingleTarget"
      },
      "effectType": "StatisticEffect",
      "Description": {
        "Id": "Guts-ImprovedResolveGeneration",
        "Name": "Improved Resolve Generation - Guts 1",
        "Details": "Improves resolve generation by 5%",
        "Icon": "uixSvgIcon_ability_mastertactician"
      },
      "statisticData": {
        "statName": "resolveGenBaseMult",
        "operation": "Float_Add",
        "modValue": "0.05",
        "modType": "System.Single"
      },
      "nature": "Buff"
    }
  ]
}
