{
  "VehicleTags": {
    "items": [
      "mr-resize-1.0",
      "unit_release",
      "unit_vehicle",
      "unit_light",
      "unit_wheels",
      "unit_lance_support",
      "unit_vehicle_mobileHQ",
      "unit_command",
      "unit_resupply",
      "unit_vehicle_apc",
      "Unit_Convoy_Command",
      "unit_generic",
      "unit_bracket_med",
      "EscorpionImperio",
      "ClanWolfInExile",
      "GreenGhosts",
      "FroncReaches",
      "wordofblake",
      "comstar",
      "steiner",
      "marik",
      "kurita",
      "davion",
      "liao",
      "locals",
      "CalderonProtectorate",
      "magistracyofcanopus",
      "marian",
      "taurianconcordat",
      "rasalhague",
      "outworld",
      "ives",
      "Rim",
      "elysia",
      "oberon",
      "valkyrate",
      "circinus",
      "illyrian",
      "lothian",
      "jarnfolk",
      "delphi",
      "hanse",
      "castile",
      "chainelane",
      "tortuga",
      "axumite",
      "FiltveltCoalition",
      "auriganpirates",
      "aurigandirectorate",
      "auriganrestoration",
      "ClanStoneLion",
      "GhostBearDominion",
      "RavenAlliance",
      "DarkCaste",
      "clansgeneric",
      "clanbloodspirit",
      "clanwolf",
      "clanfiremandrill",
      "clanstaradder",
      "clancoyote",
      "clanjadefalcon",
      "clansteelviper",
      "clanicehellion",
      "clangoliathscorpion",
      "clandiamondshark",
      "clanhellshorses",
      "clansnowraven",
      "clanghostbear",
      "clansmokejaguar",
      "clancloudcobra",
      "clannovacat",
      "clanburrock",
      "locals",
      "auriganmercenaries",
      "nofaction",
      "mercenaryreviewboard",
      "betrayers",
      "flakjackals",
      "localsbrockwayrefugees",
      "selfemployed",
      "masonsmarauders",
      "steelbeast",
      "kellhounds",
      "razorbackmercs",
      "hostilemercenaries",
      "emeralddawn",
      "siantriumphant",
      "profhorvat",
      "redhareregiment",
      "edcorbu",
      "duchyofandurien",
      "blackcalderadefense",
      "housenakano",
      "graydeathlegion",
      "blackcalderadefense_hidden",
      "selfemployed_yang",
      "securitysolutionsinc",
      "paladinprotectionllc",
      "housekhulan",
      "INVALID_UNSET",
      "NoFaction",
      "Player1sMercUnit",
      "Owner",
      "Player2sMercUnit",
      "Unknown",
      "Faction_Neutral",
      "Faction_Employer",
      "Faction_Target",
      "Faction_TargetsAlly",
      "society",
      "solaris7"
    ],
    "tagSetSourceFile": ""
  },
  "ChassisID": "vehiclechassisdef_MOBILEHQ_ARMORED",
  "Description": {
    "Cost": 972614,
    "Rarity": 0,
    "Purchasable": false,
    "UIName": "Mobile HQ (UA)",
    "Id": "vehicledef_MOBILEHQ_ARMORED",
    "Name": "Mobile HQ (UA)",
    "Details": "A Succession wars era variant of the Mobile HQ, the Armored variant trades some of the onboard Communications Gear for additional armor.\n\n<b><color=#ffcc00>Fusion: Expensive engine that works in a Vacuum.</color></b>\n\n<b><color=#ffcc00>Movement: 6/9 Hex: 180/270 Meters.</color></b>\n\n<color=#ffcc00><b>Armor:</b> Armor\n<b>Structure:</b> Structure\n<b>Values       A        S  </b>\n<b>Front</b>       127     15\n<b>Left</b>         127     15\n<b>Right</b>       127     15\n<b>Rear</b>        127     15\n<b>Turret</b>      127     15\n\n<b>Total</b>      635     75</color>\n\n<color=#ff0000>Quirk: Battle Computer B2000</color>\n\n<color=#ffcc00>Can Resupply/Repair</color>",
    "Icon": "MobileHQ"
  },
  "Locations": [
    {
      "Location": "Front",
      "CurrentArmor": 127,
      "CurrentInternalStructure": 15,
      "AssignedArmor": 127,
      "DamageLevel": "Functional"
    },
    {
      "Location": "Left",
      "CurrentArmor": 127,
      "CurrentInternalStructure": 15,
      "AssignedArmor": 127,
      "DamageLevel": "Functional"
    },
    {
      "Location": "Right",
      "CurrentArmor": 127,
      "CurrentInternalStructure": 15,
      "AssignedArmor": 127,
      "DamageLevel": "Functional"
    },
    {
      "Location": "Rear",
      "CurrentArmor": 127,
      "CurrentInternalStructure": 15,
      "AssignedArmor": 127,
      "DamageLevel": "Functional"
    },
    {
      "Location": "Turret",
      "CurrentArmor": 127,
      "CurrentInternalStructure": 15,
      "AssignedArmor": 127,
      "DamageLevel": "Functional"
    }
  ],
  "inventory": [
    {
      "MountedLocation": "Turret",
      "ComponentDefID": "Weapon_Laser_Medium",
      "ComponentDefType": "Weapon",
      "HardpointSlot": 0,
      "DamageLevel": "Functional"
    },
    {
      "MountedLocation": "Turret",
      "ComponentDefID": "Weapon_Laser_Medium",
      "ComponentDefType": "Weapon",
      "HardpointSlot": 0,
      "DamageLevel": "Functional"
    },
    {
      "MountedLocation": "Rear",
      "ComponentDefID": "Ammo_AmmunitionBox_SPAMMY",
      "ComponentDefType": "AmmunitionBox",
      "HardpointSlot": -1,
      "DamageLevel": "Functional"
    },
    {
      "MountedLocation": "Front",
      "ComponentDefID": "Default_Vehicle_Crew_Compartment",
      "ComponentDefType": "Upgrade",
      "HardpointSlot": -1,
      "DamageLevel": "Functional"
    },
    {
      "MountedLocation": "Front",
      "ComponentDefID": "Default_Vehicle_FCS_Generic_2",
      "ComponentDefType": "Upgrade",
      "HardpointSlot": -1,
      "DamageLevel": "Functional"
    },
    {
      "MountedLocation": "Front",
      "ComponentDefID": "Default_Vehicle_Sensors",
      "ComponentDefType": "Upgrade",
      "HardpointSlot": -1,
      "DamageLevel": "Functional"
    },
    {
      "MountedLocation": "Left",
      "ComponentDefID": "Default_Vehicle_Motive_Wheeled_Left",
      "ComponentDefType": "Upgrade",
      "HardpointSlot": -1,
      "DamageLevel": "Functional"
    },
    {
      "MountedLocation": "Left",
      "ComponentDefID": "Gear_ProtectivePadding",
      "ComponentDefType": "Upgrade",
      "HardpointSlot": -1,
      "DamageLevel": "Functional"
    },
    {
      "MountedLocation": "Right",
      "ComponentDefID": "Default_Vehicle_Motive_Wheeled_Right",
      "ComponentDefType": "Upgrade",
      "HardpointSlot": -1,
      "DamageLevel": "Functional"
    },
    {
      "MountedLocation": "Right",
      "ComponentDefID": "Gear_ProtectivePadding",
      "ComponentDefType": "Upgrade",
      "HardpointSlot": -1,
      "DamageLevel": "Functional"
    },
    {
      "MountedLocation": "Rear",
      "ComponentDefID": "Default_Armor_Standard",
      "ComponentDefType": "Upgrade",
      "HardpointSlot": -1,
      "DamageLevel": "Functional"
    },
    {
      "MountedLocation": "Rear",
      "ComponentDefID": "Default_Structure_Standard",
      "ComponentDefType": "Upgrade",
      "HardpointSlot": -1,
      "DamageLevel": "Functional"
    },
    {
      "MountedLocation": "Rear",
      "ComponentDefID": "Default_Vehicle_Motive_Wheeled_Defaultbox",
      "ComponentDefType": "Upgrade",
      "HardpointSlot": -1,
      "DamageLevel": "Functional"
    },
    {
      "MountedLocation": "Rear",
      "ComponentDefID": "Gear_Vehicle_CommunicationsEquipment",
      "ComponentDefType": "Upgrade",
      "HardpointSlot": -1,
      "DamageLevel": "Functional"
    },
    {
      "MountedLocation": "Rear",
      "ComponentDefID": "Gear_Vehicle_Compartment_Cargo",
      "ComponentDefType": "Upgrade",
      "HardpointSlot": -1,
      "DamageLevel": "Functional"
    },
    {
      "MountedLocation": "Rear",
      "ComponentDefID": "Quirk_BattleComputer_B2000",
      "ComponentDefType": "Upgrade",
      "HardpointSlot": -1,
      "DamageLevel": "Functional"
    },
    {
      "MountedLocation": "Turret",
      "ComponentDefID": "Default_Vehicle_Turret",
      "ComponentDefType": "Upgrade",
      "HardpointSlot": -1,
      "DamageLevel": "Functional"
    },
    {
      "MountedLocation": "Left",
      "ComponentDefID": "Gear_HeatSink_Single",
      "ComponentDefType": "HeatSink",
      "HardpointSlot": -1,
      "DamageLevel": "Functional"
    },
    {
      "MountedLocation": "Right",
      "ComponentDefID": "Gear_HeatSink_Single",
      "ComponentDefType": "HeatSink",
      "HardpointSlot": -1,
      "DamageLevel": "Functional"
    },
    {
      "MountedLocation": "Rear",
      "ComponentDefID": "Gear_EngineCore_130",
      "ComponentDefType": "HeatSink",
      "HardpointSlot": -1,
      "DamageLevel": "Functional"
    },
    {
      "MountedLocation": "Rear",
      "ComponentDefID": "Gear_Engine_Standard",
      "ComponentDefType": "HeatSink",
      "HardpointSlot": -1,
      "DamageLevel": "Functional"
    },
    {
      "MountedLocation": "Rear",
      "ComponentDefID": "Gear_HeatSink_Single",
      "ComponentDefType": "HeatSink",
      "HardpointSlot": -1,
      "DamageLevel": "Functional"
    },
    {
      "MountedLocation": "Rear",
      "ComponentDefID": "Gear_HeatSink_Single",
      "ComponentDefType": "HeatSink",
      "HardpointSlot": -1,
      "DamageLevel": "Functional"
    },
    {
      "MountedLocation": "Rear",
      "ComponentDefID": "Gear_HeatSink_Single",
      "ComponentDefType": "HeatSink",
      "HardpointSlot": -1,
      "DamageLevel": "Functional"
    },
    {
      "MountedLocation": "Rear",
      "ComponentDefID": "Gear_Vehicle_EngineCooling_CoolantSystem",
      "ComponentDefType": "HeatSink",
      "HardpointSlot": -1,
      "DamageLevel": "Functional"
    }
  ]
}