{
  "Custom": {
    "VAssemblyVariant": {
      "PrefabID": "VultureVTOL",
      "Exclude": false,
      "Include": true
    }
  },
  "CustomParts": {
    "AOEHeight": 45,
    "FiringArc": 50,
    "Unaffected": {
      "DesignMasks": "true",
      "Pathing": "true",
      "Fire": "true",
      "Landmines": "true",
      "MoveClamp": 0.5,
      "MoveCostBiome": "true",
      "AllowPartialMovement": false
    },
    "CustomParts": [],
    "CrewLocation": "None",
    "NullifyBodyMesh": true,
    "TieToGroundOnDeath": "true"
  },
  "Description": {
    "Cost": 1503500,
    "Rarity": 0,
    "Purchasable": false,
    "UIName": "Vulture Gunship (LAC/5)",
    "Id": "vehiclechassisdef_Vulture_LAC5",
    "Name": "Vulture Gunship",
    "Details": "Created during the Age of War, the Vulture series of gunships are designed to wear targets down at range and provide direct fire support for allied units. A 30 ton gunship, the Vulture is usually built around some variation of a 100 rated engine, giving it a top speed of 120 km/h; with 4-5 tons of armour on each variant. Still in irregular production, the Vulture can be found in any number of variants across most of known space.\n\n<b><color=#ffcc00>Fusion: Expensive engine that works in a Vacuum.</color></b>\n\n<b><color=#ffcc00>Movement: 8/12 hexes / 240/360 meters.</color></b>\n\n<color=#ffcc00><b>Armor:</b> Armor\n<b>Structure:</b> Structure\n<b>Values       A        S  </b>\n<b>Front</b>       120     15\n<b>Left</b>          95     15\n<b>Right</b>        95     15\n<b>Rear</b>         75     15\n\n<b>Total</b>      400     75</color>\n\n<color=#ff0000>Quirk: Easy to Pilot</color>",
    "Icon": "RedKite"
  },
  "ChassisTags": {
    "items": [
      "VTOL"
    ]
  },
  "YangsThoughts": "It's a chopper boss, whirly bit goes round.",
  "MovementCapDefID": "movedef_8-12cv",
  "movementType": "Wheeled",
  "PathingCapDefID": "pathingdef_vtol",
  "HardpointDataDefID": "hardpointdatadef_curedkite",
  "PrefabIdentifier": "chrprfmech_redkite_vtol",
  "PrefabBase": "curedkite",
  "Tonnage": 30,
  "weightClass": "LIGHT",
  "BattleValue": 564,
  "TopSpeed": 85,
  "TurnRadius": 90,
  "SpotterDistanceMultiplier": 1,
  "VisibilityMultiplier": 1,
  "SensorRangeMultiplier": 1,
  "Signature": 1,
  "Radius": 3,
  "Locations": [
    {
      "Location": "Front",
      "Hardpoints": [
        {
          "WeaponMountID": "Ballistic",
          "Omni": false
        },
        {
          "WeaponMountID": "Ballistic",
          "Omni": false
        }
      ],
      "Tonnage": 0,
      "InventorySlots": 0,
      "MaxArmor": 120,
      "InternalStructure": 15
    },
    {
      "Location": "Left",
      "Hardpoints": [],
      "Tonnage": 0,
      "InventorySlots": 0,
      "MaxArmor": 95,
      "InternalStructure": 15
    },
    {
      "Location": "Right",
      "Hardpoints": [],
      "Tonnage": 0,
      "InventorySlots": 0,
      "MaxArmor": 95,
      "InternalStructure": 15
    },
    {
      "Location": "Rear",
      "Hardpoints": [],
      "Tonnage": 0,
      "InventorySlots": 0,
      "MaxArmor": 75,
      "InternalStructure": 15
    },
    {
      "Location": "Turret",
      "Hardpoints": [],
      "Tonnage": 0,
      "InventorySlots": 0,
      "MaxArmor": 15,
      "InternalStructure": 15
    }
  ],
  "LOSSourcePositions": [
    {
      "x": 0,
      "y": 4,
      "z": -0.5
    },
    {
      "x": 0,
      "y": 2,
      "z": 3.5
    }
  ],
  "LOSTargetPositions": [
    {
      "x": 0,
      "y": 4,
      "z": -0.5
    },
    {
      "x": 0,
      "y": 2,
      "z": 3.5
    },
    {
      "x": -2,
      "y": 2,
      "z": 0
    },
    {
      "x": 2,
      "y": 2,
      "z": 0
    },
    {
      "x": 0,
      "y": 2,
      "z": -4.5
    }
  ]
}