{
  "Custom": {
    "VAssemblyVariant": {
      "PrefabID": "Durga",
      "Exclude": false,
      "Include": true
    }
  },
  "CustomParts": {
    "AOEHeight": 45,
    "FiringArc": 50,
    "Unaffected": {
      "DesignMasks": "true",
      "Pathing": "true",
      "Fire": "true",
      "Landmines": "true",
      "MoveCostBiome": "true",
      "MoveClamp": 0.5,
      "AllowPartialMovement": false
    },
    "NullifyBodyMesh": true,
    "TieToGroundOnDeath": "true",
    "CrewLocation": "None"
  },
  "Description": {
    "Cost": 5123066,
    "Rarity": 0,
    "Purchasable": false,
    "UIName": "Durga VTOL",
    "Id": "vehiclechassisdef_Durga",
    "Name": "Durga VTOL",
    "Details": "Entering service in 3024, the 25 ton Durga was developed by the Hell's Horses as a heavier version of the Donar Assault Helicopter. Weighing 4 tons more then it's predecessor, the Durga is built around a 110 rated XL Engine, making it faster then the lighter Donar. Armed with an Artemis IV enhanced LRM-15, 2 Medium Pulse Lasers and a Small Pulse Laser, the Durga is built for long range engagements; whilst still possessing a potent short range punch. Defensively an ECM Suite and Ferro Fibrous armour protect the Durga. Manufactured by both the Hell's Horses and the Diamond Sharks, the Durga has spread throughout the Clans and most field at least 1 star of them.\n\n<b><color=#ffcc00>Fusion: Expensive engine that works in a Vacuum.</color></b>\n\n<b><color=#ffcc00>Movement: 10/15 Hex: 300/450 Meters.</color></b>\n\n<color=#ffcc00><b>Armor:</b> Ferro-Fibrous (C)\n<b>Structure:</b> Structure\n<b>Values       A        S  </b>\n<b>Front</b>        95     15\n<b>Left</b>          70     15\n<b>Right</b>        70     15\n<b>Rear</b>         60     15\n\n<b>Total</b>      310     75</color>\n\n<color=#ff0000>Quirk: Anti-Air Targeting</color>",
    "Icon": "Durga"
  },
  "YangsThoughts": "It's a tank, Boss, they all look the same to me.",
  "MovementCapDefID": "movedef_10-15cv",
  "movementType": "Wheeled",
  "PathingCapDefID": "pathingdef_vtol",
  "HardpointDataDefID": "hardpointdatadef_cuwarriorvtol",
  "PrefabIdentifier": "chrprfmech_warrior_vtol",
  "PrefabBase": "cuwarriorvtol",
  "Tonnage": 25,
  "weightClass": "LIGHT",
  "BattleValue": 564,
  "TopSpeed": 85,
  "TurnRadius": 90,
  "SpotterDistanceMultiplier": 1,
  "VisibilityMultiplier": 1,
  "SensorRangeMultiplier": 1,
  "Signature": 1,
  "Radius": 3,
  "LOSSourcePositions": [
    {
      "x": 0,
      "y": 4,
      "z": -0.5
    },
    {
      "x": 0,
      "y": 2,
      "z": 3.5
    }
  ],
  "LOSTargetPositions": [
    {
      "x": 0,
      "y": 4,
      "z": -0.5
    },
    {
      "x": 0,
      "y": 2,
      "z": 3.5
    },
    {
      "x": -2,
      "y": 2,
      "z": 0
    },
    {
      "x": 2,
      "y": 2,
      "z": 0
    },
    {
      "x": 0,
      "y": 2,
      "z": -4.5
    }
  ],
  "Locations": [
    {
      "Location": "Front",
      "Hardpoints": [
        {
          "WeaponMountID": "Energy",
          "Omni": false
        },
        {
          "WeaponMountID": "Energy",
          "Omni": false
        },
        {
          "WeaponMountID": "Energy",
          "Omni": false
        },
        {
          "WeaponMountID": "Missile",
          "Omni": false
        }
      ],
      "Tonnage": 0,
      "InventorySlots": 0,
      "MaxArmor": 95,
      "InternalStructure": 15
    },
    {
      "Location": "Left",
      "Hardpoints": [],
      "Tonnage": 0,
      "InventorySlots": 0,
      "MaxArmor": 70,
      "InternalStructure": 15
    },
    {
      "Location": "Right",
      "Hardpoints": [],
      "Tonnage": 0,
      "InventorySlots": 0,
      "MaxArmor": 70,
      "InternalStructure": 15
    },
    {
      "Location": "Rear",
      "Hardpoints": [],
      "Tonnage": 0,
      "InventorySlots": 0,
      "MaxArmor": 60,
      "InternalStructure": 15
    },
    {
      "Location": "Turret",
      "Hardpoints": [],
      "Tonnage": 0,
      "InventorySlots": 0,
      "MaxArmor": 15,
      "InternalStructure": 15
    }
  ]
}
