{
  "VehicleTags": {
    "items": [
      "mr-resize-1.37",
      "unit_vehicle",
      "unit_medium",
      "unit_vtol",
      "society",
      "unit_release",
      "unit_lance_vanguard",
      "unit_advanced",
      "unit_bracket_med",
      "unit_noconvoy",
      "unit_predator",
      "Republic",
      "comstar",
      "WordOfBlake",
      "steiner",
      "marik",
      "kurita",
      "davion",
      "liao",
      "magistracyofcanopus",
      "marian",
      "taurianconcordat",
      "rasalhague",
      "outworld",
      "elysia",
      "oberon",
      "valkyrate",
      "circinus",
      "illyrian",
      "lothian",
      "hanse",
      "castile",
      "tortuga",
      "auriganpirates",
      "aurigandirectorate",
      "auriganrestoration",
      "locals",
      "clanwolf",
      "clanjadefalcon",
      "clandiamondshark",
      "clanhellshorses",
      "clansnowraven",
      "clanghostbear",
      "clannovacat"
    ],
    "tagSetSourceFile": ""
  },
  "ChassisID": "vehiclechassisdef_DI_MULTI",
  "Description": {
    "Cost": 3428794,
    "Rarity": 0,
    "Purchasable": false,
    "UIName": "DI Multipurpose VTOL",
    "Id": "vehicledef_DI_MULTI",
    "Name": "DI Multipurpose VTOL",
    "Details": "A fast unit, the Light VTOL is not designed for protracted combat. Intended as a scout or vanguard unit, the Light VTOL is constantly on the move, probing ahead of the rest of the troops.\n\n <b><color=#ffcc00>VTOL: Ignores Terrain, slow in thin atmosphere.</color></b>\n\n <b><color=#ffcc00>Fusion: Expensive engine that works in a Vacuum.</color></b>\n\n <b><color=#ffcc00>Movement: 9/14 Hex: 270/420 Meters.</color></b>\n\n<b>Armor:</b> Heavy Ferro\n<b>Structure:</b> Structure\n<b>Values       A        S  </b>\n<b>Front</b>       150     18\n<b>Left</b>         150     18\n<b>Right</b>       150     18\n<b>Rear</b>        110     18\n<b>Turret</b>       15     18\n\n<b>Total</b>      575     90\n",
    "Icon": "DIMultipurpose"
  },
  "Version": 1,
  "Locations": [
    {
      "Location": "Front",
      "CurrentArmor": 150,
      "CurrentInternalStructure": 18,
      "AssignedArmor": 150,
      "DamageLevel": "Functional"
    },
    {
      "Location": "Left",
      "CurrentArmor": 150,
      "CurrentInternalStructure": 18,
      "AssignedArmor": 150,
      "DamageLevel": "Functional"
    },
    {
      "Location": "Right",
      "CurrentArmor": 150,
      "CurrentInternalStructure": 18,
      "AssignedArmor": 150,
      "DamageLevel": "Functional"
    },
    {
      "Location": "Rear",
      "CurrentArmor": 110,
      "CurrentInternalStructure": 18,
      "AssignedArmor": 110,
      "DamageLevel": "Functional"
    },
    {
      "Location": "Turret",
      "CurrentArmor": 15,
      "CurrentInternalStructure": 18,
      "AssignedArmor": 15,
      "DamageLevel": "Functional"
    }
  ],
  "inventory": [
    {
      "MountedLocation": "Front",
      "ComponentDefID": "Weapon_Laser_TAG",
      "ComponentDefType": "Weapon",
      "HardpointSlot": 1,
      "DamageLevel": "Functional"
    },
    {
      "MountedLocation": "Front",
      "ComponentDefID": "Weapon_PPC_LIGHT",
      "ComponentDefType": "Weapon",
      "HardpointSlot": 0,
      "DamageLevel": "Functional"
    },
    {
      "MountedLocation": "Front",
      "ComponentDefID": "Gear_BeagleActiveProbe",
      "ComponentDefType": "Upgrade",
      "HardpointSlot": -1,
      "DamageLevel": "Functional"
    },
    {
      "MountedLocation": "Front",
      "ComponentDefID": "Gear_VTOL_Chin_Turret",
      "ComponentDefType": "Upgrade",
      "HardpointSlot": -1,
      "DamageLevel": "Functional"
    },
    {
      "MountedLocation": "Front",
      "ComponentDefID": "Tank_CrewCompartment",
      "ComponentDefType": "Upgrade",
      "HardpointSlot": -1,
      "DamageLevel": "Functional"
    },
    {
      "MountedLocation": "Front",
      "ComponentDefID": "Tank_FCS_Generic",
      "ComponentDefType": "Upgrade",
      "HardpointSlot": -1,
      "DamageLevel": "Functional"
    },
    {
      "MountedLocation": "Front",
      "ComponentDefID": "Tank_Sensors_Generic",
      "ComponentDefType": "Upgrade",
      "HardpointSlot": -1,
      "DamageLevel": "Functional"
    },
    {
      "MountedLocation": "Front",
      "ComponentDefID": "emod_structureslots_standard",
      "ComponentDefType": "Upgrade",
      "HardpointSlot": -1
    },
    {
      "MountedLocation": "Rear",
      "ComponentDefID": "Tank_InfantryCompartment",
      "ComponentDefType": "Upgrade",
      "HardpointSlot": -1,
      "DamageLevel": "Functional"
    },
    {
      "MountedLocation": "Rear",
      "ComponentDefID": "emod_armorslots_heavyferrosfibrous",
      "ComponentDefType": "Upgrade",
      "HardpointSlot": -1
    },
    {
      "MountedLocation": "Turret",
      "ComponentDefID": "Gear_VTOL",
      "ComponentDefType": "Upgrade",
      "HardpointSlot": -1,
      "DamageLevel": "Functional"
    },
    {
      "MountedLocation": "Rear",
      "ComponentDefID": "Gear_Engine_085",
      "ComponentDefType": "HeatSink",
      "HardpointSlot": -1,
      "DamageLevel": "Functional"
    },
    {
      "MountedLocation": "Left",
      "ComponentDefID": "emod_engineslots_size2",
      "ComponentDefType": "HeatSink",
      "HardpointSlot": -1,
      "DamageLevel": "Functional"
    },
    {
      "MountedLocation": "Right",
      "ComponentDefID": "emod_engineslots_size2",
      "ComponentDefType": "HeatSink",
      "HardpointSlot": -1,
      "DamageLevel": "Functional"
    },
    {
      "MountedLocation": "Rear",
      "ComponentDefID": "emod_engineslots_light_center",
      "ComponentDefType": "HeatSink",
      "HardpointSlot": -1,
      "DamageLevel": "Functional"
    },
    {
      "MountedLocation": "Rear",
      "ComponentDefID": "Gear_HeatSink_Generic_Standard",
      "ComponentDefType": "HeatSink",
      "HardpointSlot": -1,
      "DamageLevel": "Functional"
    },
    {
      "MountedLocation": "Rear",
      "ComponentDefID": "Gear_HeatSink_Generic_Standard",
      "ComponentDefType": "HeatSink",
      "HardpointSlot": -1,
      "DamageLevel": "Functional"
    },
    {
      "MountedLocation": "Rear",
      "ComponentDefID": "Tank_Coolant_System",
      "ComponentDefType": "HeatSink",
      "HardpointSlot": -1,
      "DamageLevel": "Functional"
    }
  ]
}
