{
  "Custom": {
    "VAssemblyVariant": {
      "PrefabID": "GremlinSerpentus",
      "Exclude": false,
      "Include": true
    }
  },
  "CustomParts": {
    "MoveCost": "Hover",
    "MoveClamp": 0.5
  },
  "Description": {
    "Cost": 42725880,
    "Rarity": 0,
    "Purchasable": false,
    "UIName": "Gremlin 0A",
    "Id": "vehiclechassisdef_Gremlin_0A",
    "Name": "Gremlin",
    "Details": "Gremlin Main Battle Tank, another Serpentus Series Vehicle, bringing the mobility of a Hover into the Heavy Bracket.\n\n <b><color=#ffcc00>Hover: Fast on open ground and water, slow in rough terrain, not very agile.</color></b>\n\n <b><color=#ffcc00>Fusion: Expensive engine that works in a Vacuum.</color></b>\n\n <b><color=#ffcc00>Movement: 8/12 Hex: 240/360 Meters.</color></b>\n\n<b>Armor:</b> Vehicle Stealth\n<b>Structure:</b> Vehicle Composite\n<b>Values       A        S  </b>\n<b>Front</b>       215     56\n<b>Left</b>         175     56\n<b>Right</b>       175     56\n<b>Rear</b>        160     56\n<b>Turret</b>      175     56\n\n<b>Total</b>      900    280\n",
    "Icon": "WraithHover"
  },
  "YangsThoughts": "It's a tank, Boss, they all look the same to me.",
  "MovementCapDefID": "movedef_8-12cv",
  "movementType": "Wheeled",
  "PathingCapDefID": "pathingdef_heavy_hover",
  "HardpointDataDefID": "hardpointdatadef_tempestmlrs",
  "PrefabIdentifier": "chrprfvhcl_tempestmlrs",
  "PrefabBase": "tempestmlrs",
  "Tonnage": 73,
  "weightClass": "HEAVY",
  "BattleValue": 800,
  "TopSpeed": 125,
  "TurnRadius": 90,
  "SpotterDistanceMultiplier": 1,
  "VisibilityMultiplier": 1,
  "SensorRangeMultiplier": 1,
  "Signature": 0,
  "Radius": 4,
  "LOSSourcePositions": [
    {
      "x": 0,
      "y": 2.5,
      "z": -0.5
    },
    {
      "x": 0,
      "y": 1.5,
      "z": 3
    }
  ],
  "LOSTargetPositions": [
    {
      "x": 0,
      "y": 2.5,
      "z": -0.5
    },
    {
      "x": 0,
      "y": 1.5,
      "z": 3
    },
    {
      "x": -2,
      "y": 2.5,
      "z": 0
    },
    {
      "x": 2,
      "y": 2.5,
      "z": 0
    },
    {
      "x": 0,
      "y": 1.5,
      "z": -4.5
    }
  ],
  "Locations": [
    {
      "Location": "Front",
      "Hardpoints": [
        {
          "WeaponMount": "Energy",
          "Omni": false
        },
        {
          "WeaponMount": "Energy",
          "Omni": false
        },
        {
          "WeaponMount": "AntiPersonnel",
          "Omni": false
        },
        {
          "WeaponMount": "AntiPersonnel",
          "Omni": false
        }
      ],
      "Tonnage": 0,
      "InventorySlots": 0,
      "MaxArmor": 215,
      "InternalStructure": 56
    },
    {
      "Location": "Left",
      "Hardpoints": [],
      "Tonnage": 0,
      "InventorySlots": 0,
      "MaxArmor": 175,
      "InternalStructure": 56
    },
    {
      "Location": "Right",
      "Hardpoints": [],
      "Tonnage": 0,
      "InventorySlots": 0,
      "MaxArmor": 175,
      "InternalStructure": 56
    },
    {
      "Location": "Rear",
      "Hardpoints": [],
      "Tonnage": 0,
      "InventorySlots": 0,
      "MaxArmor": 160,
      "InternalStructure": 56
    },
    {
      "Location": "Turret",
      "Hardpoints": [
        {
          "WeaponMount": "Ballistic",
          "Omni": false
        }
      ],
      "Tonnage": 0,
      "InventorySlots": 0,
      "MaxArmor": 175,
      "InternalStructure": 56
    }
  ]
}
