{
  "VehicleTags": {
    "items": [
      "mr-resize-2.00",
      "unit_vehicle",
      "unit_vehicle_clan",
      "unit_assault",
      "unit_tracks",
      "unit_release",
      "unit_indirectFire",
      "unit_lance_tank",
      "unit_lance_assassin",
      "unit_bracket_high",
      "clansgeneric",
      "clanbloodspirit",
      "clanwolf",
      "clanfiremandrill",
      "clanstaradder",
      "clancoyote",
      "clanjadefalcon",
      "clansteelviper",
      "clanicehellion",
      "clangoliathscorpion",
      "clandiamondshark",
      "clanhellshorses",
      "clansnowraven",
      "clanghostbear",
      "clansmokejaguar",
      "clancloudcobra",
      "clannovacat",
      "clanburrock"
    ],
    "tagSetSourceFile": ""
  },
  "ChassisID": "vehiclechassisdef_PUMA-2_CLAN",
  "Description": {
    "Cost": 34161046,
    "Rarity": 0,
    "Purchasable": false,
    "UIName": "Puma PAT-IIC-2",
    "Id": "vehicledef_PUMA-2_CLAN",
    "Name": "Puma PAT-IIC-2",
    "Details": "A clantech upgrade to the Royal Puma, this support tank is assigned to second line units.\n\n <b><color=#ffcc00>Tracked: High traction, agile turning.</color></b>\n\n <b><color=#ffcc00>Fusion: Expensive engine that works in a Vacuum.</color></b>\n\n <b><color=#ffcc00>Movement: 3/5 Hex: 90/150 Meters.</color></b>\n\n<b>Armor:</b> Armor (C)\n<b>Structure:</b> Structure\n<b>Values       A        S  </b>\n<b>Front</b>       342     50\n<b>Left</b>         240     50\n<b>Right</b>       240     50\n<b>Rear</b>        150     50\n<b>Turret</b>      288     50\n\n<b>Total</b>      1260    250\n",
    "Icon": "Puma"
  },
  "Version": 1,
  "Locations": [
    {
      "Location": "Front",
      "CurrentArmor": 342,
      "CurrentInternalStructure": 50,
      "AssignedArmor": 342,
      "DamageLevel": "Functional"
    },
    {
      "Location": "Left",
      "CurrentArmor": 240,
      "CurrentInternalStructure": 50,
      "AssignedArmor": 240,
      "DamageLevel": "Functional"
    },
    {
      "Location": "Right",
      "CurrentArmor": 240,
      "CurrentInternalStructure": 50,
      "AssignedArmor": 240,
      "DamageLevel": "Functional"
    },
    {
      "Location": "Rear",
      "CurrentArmor": 150,
      "CurrentInternalStructure": 50,
      "AssignedArmor": 150,
      "DamageLevel": "Functional"
    },
    {
      "Location": "Turret",
      "CurrentArmor": 288,
      "CurrentInternalStructure": 50,
      "AssignedArmor": 288,
      "DamageLevel": "Functional"
    }
  ],
  "inventory": [
    {
      "MountedLocation": "Front",
      "ComponentDefID": "Weapon_LRM_ATM3_CLAN",
      "ComponentDefType": "Weapon",
      "HardpointSlot": 2,
      "DamageLevel": "Functional"
    },
    {
      "MountedLocation": "Front",
      "ComponentDefID": "Weapon_LRM_ATM3_CLAN",
      "ComponentDefType": "Weapon",
      "HardpointSlot": 2,
      "DamageLevel": "Functional"
    },
    {
      "MountedLocation": "Front",
      "ComponentDefID": "Weapon_LRM_ATM3_CLAN",
      "ComponentDefType": "Weapon",
      "HardpointSlot": 2,
      "DamageLevel": "Functional"
    },
    {
      "MountedLocation": "Front",
      "ComponentDefID": "Weapon_LRM_ATM3_CLAN",
      "ComponentDefType": "Weapon",
      "HardpointSlot": 2,
      "DamageLevel": "Functional"
    },
    {
      "MountedLocation": "Front",
      "ComponentDefID": "Weapon_Laser_MediumLaserER_CLAN",
      "ComponentDefType": "Weapon",
      "HardpointSlot": 0,
      "DamageLevel": "Functional"
    },
    {
      "MountedLocation": "Front",
      "ComponentDefID": "Weapon_Laser_MediumLaserER_CLAN",
      "ComponentDefType": "Weapon",
      "HardpointSlot": 0,
      "DamageLevel": "Functional"
    },
    {
      "MountedLocation": "Left",
      "ComponentDefID": "Weapon_LRM_LRM15_CLAN",
      "ComponentDefType": "Weapon",
      "HardpointSlot": 0,
      "DamageLevel": "Functional"
    },
    {
      "MountedLocation": "Left",
      "ComponentDefID": "Weapon_LRM_LRM15_CLAN",
      "ComponentDefType": "Weapon",
      "HardpointSlot": 0,
      "DamageLevel": "Functional"
    },
    {
      "MountedLocation": "Right",
      "ComponentDefID": "Weapon_LRM_LRM15_CLAN",
      "ComponentDefType": "Weapon",
      "HardpointSlot": 0,
      "DamageLevel": "Functional"
    },
    {
      "MountedLocation": "Right",
      "ComponentDefID": "Weapon_LRM_LRM15_CLAN",
      "ComponentDefType": "Weapon",
      "HardpointSlot": 0,
      "DamageLevel": "Functional"
    },
    {
      "MountedLocation": "Turret",
      "ComponentDefID": "Weapon_PPCER_CLAN",
      "ComponentDefType": "Weapon",
      "HardpointSlot": 0,
      "DamageLevel": "Functional"
    },
    {
      "MountedLocation": "Rear",
      "ComponentDefID": "Ammo_AmmunitionBox_ArtemisIV_LRM",
      "ComponentDefType": "AmmunitionBox",
      "HardpointSlot": -1,
      "DamageLevel": "Functional"
    },
    {
      "MountedLocation": "Rear",
      "ComponentDefID": "Ammo_AmmunitionBox_ArtemisIV_LRM",
      "ComponentDefType": "AmmunitionBox",
      "HardpointSlot": -1,
      "DamageLevel": "Functional"
    },
    {
      "MountedLocation": "Rear",
      "ComponentDefID": "Ammo_AmmunitionBox_ArtemisIV_LRM",
      "ComponentDefType": "AmmunitionBox",
      "HardpointSlot": -1,
      "DamageLevel": "Functional"
    },
    {
      "MountedLocation": "Rear",
      "ComponentDefID": "Ammo_AmmunitionBox_Chaff_LRM_half",
      "ComponentDefType": "AmmunitionBox",
      "HardpointSlot": -1,
      "DamageLevel": "Functional"
    },
    {
      "MountedLocation": "Rear",
      "ComponentDefID": "Ammo_AmmunitionBox_Generic_ATM",
      "ComponentDefType": "AmmunitionBox",
      "HardpointSlot": -1,
      "DamageLevel": "Functional"
    },
    {
      "MountedLocation": "Rear",
      "ComponentDefID": "Ammo_AmmunitionBox_HE_ATM",
      "ComponentDefType": "AmmunitionBox",
      "HardpointSlot": -1,
      "DamageLevel": "Functional"
    },
    {
      "MountedLocation": "Rear",
      "ComponentDefID": "Ammo_AmmunitionBox_Swarm_LRM",
      "ComponentDefType": "AmmunitionBox",
      "HardpointSlot": -1,
      "DamageLevel": "Functional"
    },
    {
      "MountedLocation": "Rear",
      "ComponentDefID": "Ammo_AmmunitionBox_Swarm_LRM",
      "ComponentDefType": "AmmunitionBox",
      "HardpointSlot": -1,
      "DamageLevel": "Functional"
    },
    {
      "MountedLocation": "Front",
      "ComponentDefID": "Gear_Sensors_Clan",
      "ComponentDefType": "Upgrade",
      "HardpointSlot": -1
    },
    {
      "MountedLocation": "Front",
      "ComponentDefID": "Tank_CrewCompartment",
      "ComponentDefType": "Upgrade",
      "HardpointSlot": -1,
      "DamageLevel": "Functional"
    },
    {
      "MountedLocation": "Front",
      "ComponentDefID": "emod_structureslots_standard",
      "ComponentDefType": "Upgrade",
      "HardpointSlot": -1
    },
    {
      "MountedLocation": "Left",
      "ComponentDefID": "Gear_Tracked_Left",
      "ComponentDefType": "Upgrade",
      "HardpointSlot": -1,
      "DamageLevel": "Functional"
    },
    {
      "MountedLocation": "Right",
      "ComponentDefID": "Gear_Tracked_Right",
      "ComponentDefType": "Upgrade",
      "HardpointSlot": -1,
      "DamageLevel": "Functional"
    },
    {
      "MountedLocation": "Rear",
      "ComponentDefID": "Gear_Guardian_ECM_CLAN",
      "ComponentDefType": "Upgrade",
      "HardpointSlot": -1,
      "DamageLevel": "Functional"
    },
    {
      "MountedLocation": "Rear",
      "ComponentDefID": "Tank_CASE_CLAN",
      "ComponentDefType": "Upgrade",
      "HardpointSlot": -1,
      "DamageLevel": "Functional"
    },
    {
      "MountedLocation": "Rear",
      "ComponentDefID": "emod_armorslots_clstandard",
      "ComponentDefType": "Upgrade",
      "HardpointSlot": -1
    },
    {
      "MountedLocation": "Turret",
      "ComponentDefID": "Gear_FCS_Clan_ARTEMISIV",
      "ComponentDefType": "Upgrade",
      "HardpointSlot": -1,
      "DamageLevel": "Functional"
    },
    {
      "MountedLocation": "Turret",
      "ComponentDefID": "Tank_Turret",
      "ComponentDefType": "Upgrade",
      "HardpointSlot": -1,
      "DamageLevel": "Functional"
    },
    {
      "MountedLocation": "Rear",
      "ComponentDefID": "Gear_Engine_285",
      "ComponentDefType": "HeatSink",
      "HardpointSlot": -1,
      "DamageLevel": "Functional"
    },
    {
      "MountedLocation": "Left",
      "ComponentDefID": "emod_engineslots_size2",
      "ComponentDefType": "HeatSink",
      "HardpointSlot": -1,
      "DamageLevel": "Functional"
    },
    {
      "MountedLocation": "Right",
      "ComponentDefID": "emod_engineslots_size2",
      "ComponentDefType": "HeatSink",
      "HardpointSlot": -1,
      "DamageLevel": "Functional"
    },
    {
      "MountedLocation": "Rear",
      "ComponentDefID": "emod_engineslots_cxl_center",
      "ComponentDefType": "HeatSink",
      "HardpointSlot": -1,
      "DamageLevel": "Functional"
    },
    {
      "MountedLocation": "Front",
      "ComponentDefID": "Gear_HeatSink_Generic_Standard",
      "ComponentDefType": "HeatSink",
      "HardpointSlot": -1,
      "DamageLevel": "Functional"
    },
    {
      "MountedLocation": "Front",
      "ComponentDefID": "Gear_HeatSink_Generic_Standard",
      "ComponentDefType": "HeatSink",
      "HardpointSlot": -1,
      "DamageLevel": "Functional"
    },
    {
      "MountedLocation": "Front",
      "ComponentDefID": "Gear_HeatSink_Generic_Standard",
      "ComponentDefType": "HeatSink",
      "HardpointSlot": -1,
      "DamageLevel": "Functional"
    },
    {
      "MountedLocation": "Left",
      "ComponentDefID": "Gear_HeatSink_Generic_Standard",
      "ComponentDefType": "HeatSink",
      "HardpointSlot": -1,
      "DamageLevel": "Functional"
    },
    {
      "MountedLocation": "Left",
      "ComponentDefID": "Gear_HeatSink_Generic_Standard",
      "ComponentDefType": "HeatSink",
      "HardpointSlot": -1,
      "DamageLevel": "Functional"
    },
    {
      "MountedLocation": "Left",
      "ComponentDefID": "Gear_HeatSink_Generic_Standard",
      "ComponentDefType": "HeatSink",
      "HardpointSlot": -1,
      "DamageLevel": "Functional"
    },
    {
      "MountedLocation": "Right",
      "ComponentDefID": "Gear_HeatSink_Generic_Standard",
      "ComponentDefType": "HeatSink",
      "HardpointSlot": -1,
      "DamageLevel": "Functional"
    },
    {
      "MountedLocation": "Right",
      "ComponentDefID": "Gear_HeatSink_Generic_Standard",
      "ComponentDefType": "HeatSink",
      "HardpointSlot": -1,
      "DamageLevel": "Functional"
    },
    {
      "MountedLocation": "Right",
      "ComponentDefID": "Gear_HeatSink_Generic_Standard",
      "ComponentDefType": "HeatSink",
      "HardpointSlot": -1,
      "DamageLevel": "Functional"
    },
    {
      "MountedLocation": "Rear",
      "ComponentDefID": "Gear_HeatSink_Generic_Standard",
      "ComponentDefType": "HeatSink",
      "HardpointSlot": -1,
      "DamageLevel": "Functional"
    },
    {
      "MountedLocation": "Rear",
      "ComponentDefID": "Gear_HeatSink_Generic_Standard",
      "ComponentDefType": "HeatSink",
      "HardpointSlot": -1,
      "DamageLevel": "Functional"
    },
    {
      "MountedLocation": "Rear",
      "ComponentDefID": "Gear_HeatSink_Generic_Standard",
      "ComponentDefType": "HeatSink",
      "HardpointSlot": -1,
      "DamageLevel": "Functional"
    },
    {
      "MountedLocation": "Rear",
      "ComponentDefID": "Gear_HeatSink_Generic_Standard",
      "ComponentDefType": "HeatSink",
      "HardpointSlot": -1,
      "DamageLevel": "Functional"
    },
    {
      "MountedLocation": "Rear",
      "ComponentDefID": "Gear_HeatSink_Generic_Standard",
      "ComponentDefType": "HeatSink",
      "HardpointSlot": -1,
      "DamageLevel": "Functional"
    },
    {
      "MountedLocation": "Rear",
      "ComponentDefID": "Gear_HeatSink_Generic_Standard",
      "ComponentDefType": "HeatSink",
      "HardpointSlot": -1,
      "DamageLevel": "Functional"
    },
    {
      "MountedLocation": "Rear",
      "ComponentDefID": "Tank_Coolant_System",
      "ComponentDefType": "HeatSink",
      "HardpointSlot": -1,
      "DamageLevel": "Functional"
    }
  ]
}
